AlgoTree/__init__.py
AlgoTree/_utils.py
AlgoTree/builders.py
AlgoTree/dsl.py
AlgoTree/exporters.py
AlgoTree/interop.py
AlgoTree/node.py
AlgoTree/pretty_tree.py
AlgoTree/selectors.py
AlgoTree/serialization.py
AlgoTree/transformers.py
AlgoTree/tree.py
AlgoTree/shell/__init__.py
AlgoTree/shell/advanced.py
AlgoTree/shell/builtins.py
AlgoTree/shell/cli.py
AlgoTree/shell/commands.py
AlgoTree/shell/core.py
AlgoTree/shell/io_commands.py
AlgoTree/shell/shell.py
AlgoTree/shell/utils.py
algotree-2.0.2.dist-info/licenses/LICENSE
bin/__init__.py
bin/jt.py
test/__init__.py
test/test_builders.py
test/test_dsl.py
test/test_exporters.py
test/test_interop.py
test/test_node.py
test/test_piping_redirection.py
test/test_selectors.py
test/test_serialization.py
test/test_shell_commands.py
test/test_shell_core.py
test/test_transformers.py
test/test_tree.py
test/test_tree_print.py
algotree-2.0.2.dist-info/METADATA
algotree-2.0.2.dist-info/WHEEL
algotree-2.0.2.dist-info/entry_points.txt
algotree-2.0.2.dist-info/top_level.txt
algotree-2.0.2.dist-info/RECORD
