Metadata-Version: 2.4
Name: AlgoTree
Version: 2.0.2
Summary: Immutable-by-default tree manipulation library with functional programming patterns and composable transformations
Home-page: https://github.com/queelius/AlgoTree
Author: Alex Towell
Author-email: lex@metafunctor.com
Project-URL: Documentation, https://queelius.github.io/AlgoTree/
Project-URL: Source Code, https://github.com/queelius/AlgoTree
Project-URL: Issue Tracker, https://github.com/queelius/AlgoTree/issues
Project-URL: Changelog, https://github.com/queelius/AlgoTree/blob/main/CHANGELOG.md
Keywords: tree data-structure algorithms pattern-matching transformation fluent-api
Classifier: Development Status :: 5 - Production/Stable
Classifier: Intended Audience :: Developers
Classifier: Topic :: Software Development :: Libraries :: Python Modules
Classifier: Topic :: Software Development :: Libraries
Classifier: License :: OSI Approved :: MIT License
Classifier: Programming Language :: Python :: 3
Classifier: Programming Language :: Python :: 3.8
Classifier: Programming Language :: Python :: 3.9
Classifier: Programming Language :: Python :: 3.10
Classifier: Programming Language :: Python :: 3.11
Classifier: Programming Language :: Python :: 3.12
Classifier: Operating System :: OS Independent
Requires-Python: >=3.8
License-File: LICENSE
Requires-Dist: prompt_toolkit>=3.0.0
Provides-Extra: dev
Requires-Dist: sphinx; extra == "dev"
Requires-Dist: sphinx-rtd-theme; extra == "dev"
Requires-Dist: sphinxcontrib-napoleon; extra == "dev"
Requires-Dist: coverage; extra == "dev"
Requires-Dist: pytest; extra == "dev"
Requires-Dist: flake8; extra == "dev"
Provides-Extra: analytics
Requires-Dist: pandas>=1.3.0; extra == "analytics"
Requires-Dist: pyarrow>=6.0.0; extra == "analytics"
Provides-Extra: jupyter
Requires-Dist: ipywidgets>=7.6.0; extra == "jupyter"
Requires-Dist: IPython>=7.0.0; extra == "jupyter"
Dynamic: author
Dynamic: author-email
Dynamic: classifier
Dynamic: description
Dynamic: description-content-type
Dynamic: home-page
Dynamic: keywords
Dynamic: license-file
Dynamic: project-url
Dynamic: provides-extra
Dynamic: requires-dist
Dynamic: requires-python
Dynamic: summary
